README.md
setup.py
dacktool/__init__.py
dacktool.egg-info/PKG-INFO
dacktool.egg-info/SOURCES.txt
dacktool.egg-info/dependency_links.txt
dacktool.egg-info/top_level.txt
dacktool/data/__init__.py
dacktool/data/treat.py
dacktool/format/__init__.py
dacktool/format/date.py
dacktool/format/number.py
dacktool/format/print_colors.py
dacktool/format/text.py