Metadata-Version: 2.1
Name: dacktool
Version: 0.0.4
Summary: Some python tools
Home-page: https://github.com/dacker-team/dacktool
Author: Dacker
Author-email: hello@dacker.co
License: UNKNOWN
Platform: UNKNOWN
Classifier: Programming Language :: Python :: 3
Classifier: License :: OSI Approved :: MIT License
Classifier: Operating System :: OS Independent
Requires-Python: >=3
